Metadata-Version: 2.1
Name: auto-sql
Version: 0.0.2
Summary: auto_sql is a memory aware csv to sqlite converter.
Home-page: https://github.com/brettvanderwerff/auto_sql
Author: Brett Vanderwerff
Author-email: brett.vanderwerff@gmail.com
License: UNKNOWN
Platform: UNKNOWN
Classifier: Programming Language :: Python :: 3.4
Classifier: Programming Language :: Python :: 3.5
Classifier: Programming Language :: Python :: 3.6
Classifier: Operating System :: OS Independent
Classifier: License :: OSI Approved :: GNU General Public License v2 (GPLv2)
Classifier: Operating System :: OS Independent
Classifier: Development Status :: 3 - Alpha
